lyceum/__init__.py
lyceum/logic.py
lyceum/repr.py
lyceum/structure.py
lyceum/utils.py
lyceum-0.11.0.dist-info/LICENSE
lyceum-0.11.0.dist-info/WHEEL
lyceum-0.11.0.dist-info/METADATA
lyceum-0.11.0.dist-info/RECORD
