Metadata-Version: 2.1
Name: lyceum
Version: 0.11.0
Summary: Un paquet Python utile pour la programmation en lycée.
Author-email: Benjamin Abel <dev.abel@free.fr>
Classifier: Development Status :: 2 - Pre-Alpha
Classifier: Intended Audience :: Education
Classifier: License :: OSI Approved :: ISC License (ISCL)
Classifier: Natural Language :: French
Classifier: Programming Language :: Python :: 3
Requires-Dist: watchdog ; extra == "dev"
Requires-Dist: flit ; extra == "dev"
Requires-Dist: black ; extra == "dev"
Requires-Dist: flake8 ; extra == "dev"
Requires-Dist: isort ; extra == "dev"
Requires-Dist: sphinx ; extra == "doc"
Requires-Dist: sphinx_rtd_theme ; extra == "doc"
Requires-Dist: myst_nb ; extra == "doc"
Requires-Dist: pytest>=6.2.5 ; extra == "test"
Project-URL: Documentation, https://benabel.frama.io/lyceum-py
Project-URL: Home, https://framagit.org/benabel/lyceum-py
Project-URL: Source, https://framagit.org/benabel/lyceum-py
Provides-Extra: dev
Provides-Extra: doc
Provides-Extra: test
